spensireli/aws_cdk_guardduty/__init__.py
spensireli/aws_cdk_guardduty/py.typed
spensireli/aws_cdk_guardduty/_jsii/__init__.py
spensireli/aws_cdk_guardduty/_jsii/cdk-guardduty@0.0.4.jsii.tgz
spensireli_aws_cdk_guardduty-0.0.4.dist-info/LICENSE
spensireli_aws_cdk_guardduty-0.0.4.dist-info/METADATA
spensireli_aws_cdk_guardduty-0.0.4.dist-info/WHEEL
spensireli_aws_cdk_guardduty-0.0.4.dist-info/top_level.txt
spensireli_aws_cdk_guardduty-0.0.4.dist-info/RECORD
